MANIFEST.in
setup.py
src/metrium/__init__.py
src/metrium/main.py
src/metrium/metrium.wsgi
src/metrium.egg-info/PKG-INFO
src/metrium.egg-info/SOURCES.txt
src/metrium.egg-info/dependency_links.txt
src/metrium.egg-info/not-zip-safe
src/metrium.egg-info/requires.txt
src/metrium.egg-info/top_level.txt
src/metrium/bots/__init__.py
src/metrium/bots/base.py
src/metrium/bots/github_bot.py
src/metrium/bots/imap_bot.py
src/metrium/bots/omni_bot.py
src/metrium/bots/pending_bot.py
src/metrium/bots/twitter_bot.py
src/metrium/models/__init__.py
src/metrium/models/account.py
src/metrium/models/base.py
src/metrium/models/conversation.py
src/metrium/models/debug.py
src/metrium/models/github.py
src/metrium/models/log.py
src/metrium/models/mail.py
src/metrium/models/omni.py
src/metrium/models/pending.py
src/metrium/models/config/__init__.py
src/metrium/models/config/base.py
src/metrium/models/config/basic_c.py
src/metrium/models/config/github_c.py
src/metrium/models/config/mail_c.py
src/metrium/models/config/omni_c.py
src/metrium/models/config/pending_c.py
src/metrium/static/css/layout.css
src/metrium/static/images/arrows.png
src/metrium/static/images/background.png
src/metrium/static/images/circle_medium.png
src/metrium/static/images/circle_small.png
src/metrium/static/images/favicon.ico
src/metrium/static/images/logo.png
src/metrium/static/images/markers.png
src/metrium/static/images/markers_large.png
src/metrium/static/images/transparent-black.png
src/metrium/static/images/transparent-white.png
src/metrium/static/images/logos/coca_cola.png
src/metrium/static/images/logos/hive.png
src/metrium/static/images/logos/lugar_da_joia.png
src/metrium/static/js/apply.part.js
src/metrium/static/js/footer.part.js
src/metrium/static/js/header.part.js
src/metrium/static/js/main-min.js
src/metrium/static/js/main.js
src/metrium/static/js/base/dashboard.part.js
src/metrium/static/js/base/global_commits.part.js
src/metrium/static/js/base/global_sales.part.js
src/metrium/static/js/base/line_chart.part.js
src/metrium/static/js/base/log.part.js
src/metrium/static/js/base/pending.part.js
src/metrium/static/js/base/progress.part.js
src/metrium/static/js/base/pusher.part.js
